{
    "requests": [
        {
            "brickfield": [29652010, 71521809, 44134684],
            "mySide": 0,
            "steelfield": [2097152, 43008, 32],
            "waterfield": [33587200, 0, 2050]
        },
        [0, 3],
        [0, 3],
        [0, 0],
        [3, 0],
        [4, 0],
        [0, 1],
        [-1, 5],
        [4, 1],
        [-1, 5],
        [4, 1],
        [-1, 0],
        [4, 0],
        [-1, 3],
        [4, 0],
        [-1, 0],
        [4, 0],
        [-1, 5],
        [4, -1]
    ],
    "responses": [
        [2, 1],
        [2, 1],
        [2, 2],
        [1, 2],
        [6, 2],
        [2, 3],
        [-1, -1],
        [2, 3],
        [-1, 3],
        [-1, 6],
        [-1, -1],
        [-1, 6],
        [-1, -1],
        [-1, 6],
        [-1, -1],
        [-1, 6],
        [-1, -1],
        [-1, 6]
    ]
}